polyswarmdconfig/__init__.py
polyswarmdconfig/artifact.py
polyswarmdconfig/artifactclient.py
polyswarmdconfig/auth.py
polyswarmdconfig/config.py
polyswarmdconfig/consul.py
polyswarmdconfig/exceptions.py
polyswarmdconfig/kafka.py
polyswarmdconfig/profiler.py
polyswarmdconfig/redis.py
polyswarmd_config-0.1.1.dist-info/LICENSE
polyswarmd_config-0.1.1.dist-info/METADATA
polyswarmd_config-0.1.1.dist-info/WHEEL
polyswarmd_config-0.1.1.dist-info/top_level.txt
polyswarmd_config-0.1.1.dist-info/RECORD
