Metadata-Version: 2.1
Name: polyswarmd-config
Version: 0.1.1
Summary: Config module the PolySwarm Daemon
Home-page: https://github.com/polyswarm/polyswarmd-config
Author: PolySwarm Developers
Author-email: info@polyswarm.io
License: MIT
Platform: UNKNOWN
Classifier: Intended Audience :: Developers
Classifier: License :: OSI Approved :: MIT License
Classifier: Operating System :: OS Independent
Classifier: Programming Language :: Python :: 3.6
Classifier: Programming Language :: Python :: 3.7
Requires-Dist: python-consul (==1.1.0)
Requires-Dist: redis (>=3.5.3)
Requires-Dist: dataclasses (==0.7) ; python_version == "3.6"
